{"stat.useItem.minecraft.bow":151,"stat.leaveGame":15,"stat.craftItem.flammpfeil.slashblade.slashbladesilverbamboolight":5,"stat.craftItem.minecraft.iron_axe":8,"stat.mineBlock.minecraft.sandstone":1,"stat.pickup.minecraft.glowstone_dust":39,"stat.pickup.minecraft.porkchop":124,"stat.useItem.flammpfeil.slashblade.slashbladewhite":113,"stat.breakItem.flammpfeil.slashblade.slashbladewhite":2,"stat.useItem.minecraft.water_bucket":98,"stat.pickup.minecraft.rotten_flesh":65,"stat.pickup.minecraft.sand":2,"stat.useItem.minecraft.golden_sword":41,"stat.entityKilledBy.Spider":1,"stat.craftItem.minecraft.stone_axe":1,"stat.killEntity.Enderman":1,"stat.pickup.minecraft.brown_mushroom":1,"stat.mineBlock.minecraft.sand":1,"stat.killEntity.Witch":1,"stat.mineBlock.openblocks.grave":3,"stat.pickup.twilightforest.cicada":2,"stat.useItem.minecraft.iron_pickaxe":915,"stat.craftItem.flammpfeil.slashblade.slashbladebamboolight":9,"stat.useItem.minecraft.oak_stairs":151,"stat.furnaceInteraction":87,"stat.useItem.minecraft.pumpkin_seeds":27,"stat.craftItem.minecraft.pumpkin_seeds":28,"stat.killEntity.ZombieVillager":1,"stat.drop.openblocks.info_book":1,"stat.pickup.minecraft.beef":78,"stat.pickup.minecraft.iron_chestplate":2,"stat.useItem.minecraft.fence":51,"stat.drop.flammpfeil.slashblade.slashbladenamed":1,"stat.mineBlock.minecraft.fence":12,"stat.useItem.minecraft.wheat_seeds":534,"stat.pickup.twilightforest.raven_feather":1,"stat.pickup.minecraft.acacia_stairs":3,"stat.useItem.minecraft.dye":327,"stat.mineBlock.minecraft.oak_stairs":72,"stat.breakItem.flammpfeil.slashblade.slashblade":1,"stat.deaths":8,"stat.pickup.minecraft.egg":13,"stat.craftItem.minecraft.melon_seeds":2,"stat.playOneMinute":501298,"stat.craftItem.minecraft.iron_pickaxe":7,"stat.mineBlock.minecraft.tallgrass":414,"stat.chestOpened":518,"stat.pickup.minecraft.pumpkin":13,"stat.craftItem.minecraft.sign":3,"stat.useItem.minecraft.stone":270,"stat.craftItem.minecraft.carpet":3,"stat.pickup.minecraft.arrow":70,"stat.pickup.minecraft.gold_nugget":45,"stat.craftItem.minecraft.iron_hoe":3,"stat.fallOneCm":92908,"stat.pickup.minecraft.carrot":425,"stat.crouchOneCm":22012,"stat.craftItem.minecraft.iron_ingot":18,"stat.pickup.minecraft.painting":1,"stat.pickup.minecraft.red_mushroom":1,"stat.useItem.minecraft.iron_hoe":449,"stat.craftingTableInteraction":67,"stat.mineBlock.minecraft.log2":126,"stat.pickup.minecraft.feather":25,"stat.useItem.minecraft.furnace":1,"stat.useItem.minecraft.reeds":1,"stat.craftItem.minecraft.wooden_sword":12,"stat.pickup.minecraft.dye":107,"stat.pickup.minecraft.planks":6,"stat.pickup.minecraft.iron_leggings":1,"stat.pickup.minecraft.wheat_seeds":839,"stat.mineBlock.minecraft.gravel":43,"stat.useItem.minecraft.stone_pickaxe":148,"stat.craftItem.minecraft.iron_leggings":2,"stat.useItem.minecraft.stone_sword":26,"stat.craftItem.minecraft.oak_stairs":44,"stat.mineBlock.minecraft.dirt":3272,"stat.useItem.minecraft.torch":502,"stat.useItem.minecraft.bread":37,"stat.pickup.flammpfeil.slashblade.proudsoul":14,"stat.pickup.minecraft.crafting_table":1,"stat.useItem.minecraft.cobblestone":53,"stat.mineBlock.minecraft.double_plant":11,"stat.pickup.minecraft.log":311,"stat.useItem.minecraft.yellow_flower":1,"stat.pickup.minecraft.chicken":29,"stat.pickup.minecraft.sapling":216,"stat.pickup.minecraft.apple":46,"stat.pickup.minecraft.beetroot":3,"stat.craftItem.minecraft.bucket":2,"stat.craftItem.minecraft.planks":436,"stat.pickup.minecraft.book":84,"stat.useItem.minecraft.stonebrick":1,"stat.mineBlock.minecraft.log":329,"stat.pickup.minecraft.golden_sword":1,"stat.craftItem.minecraft.cooked_chicken":8,"stat.pickup.minecraft.red_flower":12,"stat.useItem.minecraft.beetroot_seeds":17,"stat.sneakTime":7005,"stat.pickup.minecraft.wool":10,"stat.pickup.minecraft.yellow_flower":11,"stat.pickup.minecraft.chest":1,"stat.pickup.minecraft.bone":60,"stat.mineBlock.minecraft.acacia_stairs":3,"stat.useItem.flammpfeil.slashblade.slashblade":88,"stat.useItem.minecraft.iron_axe":552,"stat.mineBlock.minecraft.cobblestone":2,"stat.mineBlock.minecraft.pumpkin":13,"stat.pickup.minecraft.stone_pickaxe":3,"stat.pickup.minecraft.flint":81,"stat.mineBlock.minecraft.yellow_flower":3,"stat.mineBlock.minecraft.acacia_fence":1,"stat.swimOneCm":68876,"stat.climbOneCm":605,"stat.craftItem.minecraft.arrow":96,"stat.useItem.minecraft.dirt":1851,"stat.useItem.minecraft.stone_slab2":135,"stat.pickup.minecraft.bow":4,"stat.pickup.minecraft.iron_boots":1,"stat.craftItem.minecraft.furnace":3,"stat.useItem.minecraft.red_flower":5,"stat.craftItem.minecraft.lapis_block":1,"stat.craftItem.minecraft.iron_boots":2,"stat.pickup.minecraft.coal_ore":9,"stat.craftItem.minecraft.stone_pickaxe":2,"stat.craftItem.minecraft.cooked_beef":48,"stat.craftItem.flammpfeil.slashblade.proudsoul":31,"stat.pickup.minecraft.cobblestone":960,"stat.mineBlock.minecraft.carpet":1,"stat.craftItem.minecraft.bow":1,"stat.craftItem.twilightforest.twilight_oak_stairs":8,"stat.useItem.minecraft.stone_shovel":679,"stat.flyOneCm":1144343,"stat.pickup.minecraft.glass_bottle":1,"stat.pickup.minecraft.sandstone":1,"stat.useItem.minecraft.cooked_beef":14,"stat.pickup.minecraft.redstone":265,"stat.mineBlock.minecraft.iron_ore":428,"stat.timeSinceDeath":104198,"stat.useItem.minecraft.sign":2,"stat.pickup.minecraft.mutton":2,"stat.pickup.minecraft.stonebrick":9,"stat.useItem.minecraft.cooked_porkchop":15,"stat.pickup.minecraft.carpet":1,"stat.mineBlock.minecraft.coal_ore":962,"stat.killEntity.Creeper":11,"stat.talkedToVillager":55,"stat.pickup.minecraft.string":24,"stat.entityKilledBy.Skeleton":1,"stat.craftItem.minecraft.stone_slab2":0,"stat.sprintOneCm":594882,"stat.craftItem.minecraft.stick":350,"stat.mineBlock.minecraft.diamond_ore":15,"stat.useItem.minecraft.carrot":212,"stat.useItem.minecraft.bucket":97,"stat.entityKilledBy.Creeper":1,"stat.useItem.flammpfeil.slashblade.slashbladewood":399,"stat.mineBlock.minecraft.planks":5,"stat.drop":3,"stat.pickup.flammpfeil.slashblade.slashbladewood":4,"stat.pickup.minecraft.slime_ball":2,"stat.craftItem.minecraft.emerald":7,"stat.useItem.minecraft.melon_seeds":1,"stat.killEntity.Zombie":50,"stat.craftItem.minecraft.dye":333,"stat.mineBlock.minecraft.gold_ore":64,"stat.diveOneCm":32991,"stat.pickup.minecraft.wheat":396,"stat.pickup.minecraft.sign":1,"stat.pickup.minecraft.gravel":37,"stat.craftItem.minecraft.cooked_porkchop":18,"stat.pickup.minecraft.stone_axe":2,"stat.useItem.minecraft.apple":20,"stat.useItem.minecraft.porkchop":1,"stat.useItem.minecraft.carpet":3,"stat.pickup.twilightforest.torchberries":1,"stat.useItem.minecraft.rotten_flesh":11,"stat.jump":5934,"stat.pickup.minecraft.fence":13,"stat.useItem.minecraft.wooden_hoe":36,"stat.pickup.minecraft.coal":987,"stat.pickup.minecraft.iron_helmet":1,"stat.pickup.minecraft.iron_ingot":1,"stat.craftItem.flammpfeil.slashblade.slashbladewood":12,"stat.useItem.minecraft.stone_axe":113,"stat.pickup.minecraft.gunpowder":15,"stat.craftItem.minecraft.bread":54,"stat.pickup.minecraft.spider_eye":8,"stat.craftItem.minecraft.torch":492,"stat.pickup.minecraft.dirt":3396,"stat.craftItem.minecraft.iron_helmet":2,"stat.useItem.minecraft.cooked_chicken":3,"stat.pickup.minecraft.iron_ore":427,"stat.pickup.minecraft.gold_ore":64,"stat.useItem.minecraft.sapling":130,"stat.mineBlock.minecraft.lapis_ore":17,"stat.damageTaken":6626,"stat.pickup.minecraft.leather":52,"stat.pickup.twilightforest.firefly":1,"stat.mineBlock.minecraft.red_flower":13,"stat.mineBlock.minecraft.torch":26,"stat.useItem.minecraft.wooden_pickaxe":99,"stat.tradedWithVillager":7,"stat.pickup.twilightforest.canopy_planks":14,"stat.pickup.minecraft.log2":126,"stat.pickup.minecraft.reeds":19,"stat.pickup.minecraft.bed":3,"stat.pickup.minecraft.potato":85,"stat.pickup.minecraft.oak_stairs":72,"stat.damageDealt":23096,"stat.sleepInBed":5,"stat.craftItem.minecraft.baked_potato":14,"stat.craftItem.flammpfeil.slashblade.slashbladewhite":3,"stat.killEntity.Cow":40,"stat.killEntity.Pig":52,"stat.walkOneCm":2930906,"stat.animalsBred":43,"stat.useItem.minecraft.chest":2,"stat.pickup.minecraft.stick":55,"stat.useItem.flammpfeil.slashblade.slashbladesilverbamboolight":135,"stat.pickup.openblocks.info_book":1,"stat.pickup.minecraft.stone":3224,"stat.craftItem.minecraft.iron_chestplate":2,"stat.pickup.minecraft.ender_pearl":3,"stat.pickup.minecraft.gold_ingot":1,"stat.killEntity.Skeleton":41,"stat.mineBlock.minecraft.stonebrick":5,"stat.killEntity.Chicken":29,"stat.killEntity.Spider":21,"stat.mobKills":264,"stat.mineBlock.minecraft.bookshelf":28,"stat.pickup.minecraft.quartz":106,"stat.craftItem.minecraft.fence":78,"stat.pickup.minecraft.diamond":15,"stat.mineBlock.minecraft.leaves":2644,"stat.pickup.minecraft.beetroot_seeds":18,"stat.pickup.minecraft.torch":291,"stat.mineBlock.minecraft.redstone_ore":60,"stat.craftItem.minecraft.coal_block":1,"stat.drop.minecraft.stone_axe":1,"stat.mineBlock.minecraft.stone":4834}