{"stat.useItem.minecraft.bow":392,"stat.pickup.minecraft.wooden_slab":19,"stat.leaveGame":17,"stat.useItem.minecraft.bookshelf":15,"stat.craftItem.flammpfeil.slashblade.slashbladesilverbamboolight":5,"stat.craftItem.minecraft.iron_axe":15,"stat.mineBlock.minecraft.sandstone":1,"stat.useItem.minecraft.planks":4,"stat.pickup.minecraft.glowstone_dust":39,"stat.pickup.minecraft.porkchop":322,"stat.useItem.flammpfeil.slashblade.slashbladewhite":113,"stat.breakItem.flammpfeil.slashblade.slashbladewhite":2,"stat.useItem.minecraft.water_bucket":169,"stat.pickup.minecraft.rotten_flesh":202,"stat.pickup.minecraft.sand":11,"stat.useItem.minecraft.golden_sword":41,"stat.entityKilledBy.Spider":1,"stat.craftItem.minecraft.stone_axe":1,"stat.killEntity.Enderman":2,"stat.mineBlock.minecraft.wooden_slab":17,"stat.craftItem.minecraft.iron_shovel":8,"stat.pickup.minecraft.brown_mushroom":1,"stat.mineBlock.minecraft.sand":11,"stat.killEntity.Witch":6,"stat.mineBlock.openblocks.grave":4,"stat.pickup.twilightforest.cicada":3,"stat.useItem.minecraft.iron_pickaxe":1873,"stat.useItem.minecraft.iron_shovel":305,"stat.craftItem.flammpfeil.slashblade.slashbladebamboolight":9,"stat.useItem.minecraft.oak_stairs":373,"stat.furnaceInteraction":164,"stat.useItem.minecraft.pumpkin_seeds":39,"stat.craftItem.minecraft.pumpkin_seeds":36,"stat.killEntity.ZombieVillager":7,"stat.drop.openblocks.info_book":1,"stat.pickup.minecraft.beef":139,"stat.pickup.minecraft.iron_chestplate":3,"stat.useItem.minecraft.fence":92,"stat.drop.flammpfeil.slashblade.slashbladenamed":1,"stat.mineBlock.minecraft.fence":17,"stat.useItem.minecraft.wheat_seeds":1020,"stat.pickup.twilightforest.raven_feather":1,"stat.pickup.minecraft.acacia_stairs":3,"stat.pickup.minecraft.pumpkin_seeds":19,"stat.useItem.minecraft.dye":358,"stat.mineBlock.minecraft.oak_stairs":236,"stat.breakItem.flammpfeil.slashblade.slashblade":1,"stat.deaths":9,"stat.pickup.minecraft.egg":53,"stat.craftItem.minecraft.melon_seeds":2,"stat.playOneMinute":819963,"stat.craftItem.minecraft.iron_pickaxe":11,"stat.mineBlock.minecraft.tallgrass":650,"stat.chestOpened":617,"stat.pickup.minecraft.pumpkin":78,"stat.craftItem.minecraft.sign":12,"stat.useItem.minecraft.stone":388,"stat.craftItem.minecraft.carpet":6,"stat.pickup.minecraft.arrow":150,"stat.pickup.minecraft.gold_nugget":45,"stat.craftItem.minecraft.coal":636,"stat.craftItem.minecraft.iron_hoe":6,"stat.fallOneCm":141770,"stat.pickup.minecraft.carrot":1021,"stat.crouchOneCm":47822,"stat.craftItem.minecraft.iron_ingot":91,"stat.pickup.minecraft.painting":1,"stat.pickup.minecraft.red_mushroom":1,"stat.useItem.minecraft.iron_hoe":683,"stat.craftingTableInteraction":114,"stat.mineBlock.minecraft.log2":168,"stat.pickup.minecraft.feather":93,"stat.useItem.minecraft.furnace":1,"stat.useItem.minecraft.reeds":13,"stat.craftItem.minecraft.wooden_sword":12,"stat.pickup.minecraft.dye":147,"stat.pickup.minecraft.planks":6,"stat.pickup.minecraft.iron_leggings":2,"stat.pickup.minecraft.wheat_seeds":1593,"stat.mineBlock.minecraft.gravel":46,"stat.useItem.minecraft.stone_pickaxe":148,"stat.craftItem.minecraft.iron_leggings":3,"stat.useItem.minecraft.stone_sword":26,"stat.craftItem.minecraft.oak_stairs":104,"stat.mineBlock.minecraft.dirt":4022,"stat.pickup.minecraft.poisonous_potato":1,"stat.drop.minecraft.stick":1,"stat.useItem.minecraft.torch":799,"stat.useItem.minecraft.bread":40,"stat.pickup.flammpfeil.slashblade.proudsoul":15,"stat.pickup.minecraft.crafting_table":1,"stat.useItem.minecraft.cobblestone":116,"stat.mineBlock.minecraft.double_plant":16,"stat.pickup.minecraft.log":311,"stat.pickup.minecraft.iron_pickaxe":3,"stat.useItem.minecraft.yellow_flower":2,"stat.pickup.minecraft.chicken":92,"stat.pickup.minecraft.sapling":236,"stat.pickup.minecraft.apple":46,"stat.pickup.minecraft.beetroot":61,"stat.craftItem.minecraft.bucket":2,"stat.craftItem.minecraft.planks":976,"stat.itemEnchanted":1,"stat.pickup.minecraft.book":84,"stat.useItem.minecraft.stonebrick":4,"stat.mineBlock.minecraft.log":329,"stat.pickup.minecraft.golden_sword":1,"stat.craftItem.minecraft.cooked_chicken":78,"stat.pickup.minecraft.red_flower":19,"stat.useItem.minecraft.beetroot_seeds":115,"stat.sneakTime":13465,"stat.pickup.minecraft.wool":48,"stat.pickup.minecraft.yellow_flower":13,"stat.pickup.minecraft.chest":1,"stat.pickup.minecraft.bone":91,"stat.mineBlock.minecraft.acacia_stairs":3,"stat.useItem.flammpfeil.slashblade.slashblade":88,"stat.useItem.minecraft.iron_axe":1510,"stat.mineBlock.minecraft.cobblestone":19,"stat.mineBlock.minecraft.pumpkin":78,"stat.pickup.minecraft.stone_pickaxe":3,"stat.pickup.minecraft.flint":81,"stat.mineBlock.minecraft.yellow_flower":5,"stat.craftItem.minecraft.stone_brick_stairs":4,"stat.mineBlock.minecraft.acacia_fence":1,"stat.swimOneCm":115575,"stat.climbOneCm":605,"stat.pickup.minecraft.cooked_porkchop":51,"stat.craftItem.minecraft.arrow":352,"stat.useItem.minecraft.dirt":2241,"stat.useItem.minecraft.stone_slab2":225,"stat.pickup.minecraft.bow":7,"stat.pickup.minecraft.iron_boots":2,"stat.craftItem.minecraft.furnace":3,"stat.useItem.minecraft.red_flower":10,"stat.craftItem.minecraft.lapis_block":1,"stat.craftItem.minecraft.iron_boots":3,"stat.pickup.minecraft.coal_ore":9,"stat.craftItem.minecraft.stone_pickaxe":2,"stat.craftItem.minecraft.cooked_beef":100,"stat.mineBlock.minecraft.obsidian":181,"stat.craftItem.flammpfeil.slashblade.proudsoul":31,"stat.pickup.minecraft.cobblestone":1839,"stat.mineBlock.minecraft.carpet":5,"stat.craftItem.minecraft.bow":3,"stat.craftItem.twilightforest.twilight_oak_stairs":8,"stat.useItem.minecraft.stone_shovel":946,"stat.flyOneCm":1743269,"stat.pickup.minecraft.glass_bottle":2,"stat.pickup.minecraft.sandstone":1,"stat.useItem.minecraft.cooked_beef":31,"stat.craftItem.minecraft.wooden_slab":285,"stat.pickup.minecraft.redstone":266,"stat.mineBlock.minecraft.iron_ore":629,"stat.timeSinceDeath":46533,"stat.useItem.minecraft.sign":10,"stat.useItem.minecraft.wooden_slab":137,"stat.pickup.minecraft.mutton":46,"stat.useItem.minecraft.potato":209,"stat.pickup.minecraft.stonebrick":9,"stat.useItem.minecraft.cooked_porkchop":36,"stat.pickup.minecraft.carpet":5,"stat.mineBlock.minecraft.coal_ore":1352,"stat.killEntity.Creeper":27,"stat.talkedToVillager":61,"stat.pickup.minecraft.string":39,"stat.entityKilledBy.Skeleton":2,"stat.craftItem.minecraft.stone_slab2":0,"stat.sprintOneCm":1010434,"stat.craftItem.minecraft.stick":654,"stat.craftItem.minecraft.stone":128,"stat.mineBlock.minecraft.diamond_ore":15,"stat.useItem.minecraft.diamond_pickaxe":21,"stat.useItem.minecraft.carrot":428,"stat.useItem.minecraft.bucket":97,"stat.entityKilledBy.Creeper":1,"stat.useItem.flammpfeil.slashblade.slashbladewood":399,"stat.pickup.minecraft.sugar":1,"stat.mineBlock.minecraft.planks":5,"stat.drop":4,"stat.pickup.flammpfeil.slashblade.slashbladewood":4,"stat.killEntity.Sheep":30,"stat.pickup.minecraft.slime_ball":2,"stat.craftItem.minecraft.emerald":7,"stat.craftItem.minecraft.diamond_pickaxe":1,"stat.useItem.minecraft.melon_seeds":1,"stat.killEntity.Zombie":102,"stat.craftItem.minecraft.dye":447,"stat.mineBlock.minecraft.gold_ore":103,"stat.diveOneCm":45867,"stat.pickup.minecraft.wheat":807,"stat.pickup.minecraft.sign":5,"stat.pickup.minecraft.gravel":37,"stat.craftItem.minecraft.cooked_porkchop":106,"stat.pickup.minecraft.stone_axe":2,"stat.useItem.minecraft.apple":20,"stat.pickup.minecraft.obsidian":181,"stat.useItem.minecraft.porkchop":1,"stat.useItem.minecraft.carpet":9,"stat.pickup.twilightforest.torchberries":1,"stat.useItem.minecraft.rotten_flesh":11,"stat.jump":9767,"stat.pickup.minecraft.fence":55,"stat.useItem.minecraft.wooden_hoe":36,"stat.pickup.minecraft.coal":1624,"stat.pickup.minecraft.iron_helmet":1,"stat.pickup.minecraft.iron_ingot":1,"stat.craftItem.flammpfeil.slashblade.slashbladewood":12,"stat.useItem.minecraft.stone_axe":113,"stat.pickup.minecraft.gunpowder":40,"stat.craftItem.minecraft.bread":89,"stat.pickup.minecraft.spider_eye":17,"stat.craftItem.minecraft.torch":884,"stat.pickup.minecraft.dirt":4165,"stat.craftItem.minecraft.iron_helmet":3,"stat.useItem.minecraft.cooked_chicken":6,"stat.pickup.minecraft.iron_ore":716,"stat.pickup.minecraft.gold_ore":130,"stat.useItem.minecraft.sapling":130,"stat.mineBlock.minecraft.lapis_ore":18,"stat.pickup.minecraft.iron_axe":3,"stat.mineBlock.minecraft.leaves2":411,"stat.brewingstandInteraction":1,"stat.damageTaken":9590,"stat.pickup.minecraft.leather":83,"stat.pickup.twilightforest.firefly":2,"stat.useItem.minecraft.stone_brick_stairs":2,"stat.mineBlock.minecraft.red_flower":20,"stat.mineBlock.minecraft.torch":40,"stat.useItem.minecraft.wooden_pickaxe":99,"stat.tradedWithVillager":7,"stat.pickup.twilightforest.canopy_planks":14,"stat.pickup.minecraft.log2":162,"stat.pickup.minecraft.reeds":40,"stat.pickup.minecraft.bed":3,"stat.pickup.minecraft.potato":486,"stat.pickup.minecraft.oak_stairs":236,"stat.damageDealt":51298,"stat.sleepInBed":16,"stat.craftItem.minecraft.baked_potato":14,"stat.craftItem.flammpfeil.slashblade.slashbladewhite":3,"stat.killEntity.Cow":67,"stat.killEntity.Pig":153,"stat.walkOneCm":5113730,"stat.animalsBred":128,"stat.useItem.minecraft.chest":2,"stat.playerKills":1,"stat.pickup.minecraft.stick":58,"stat.useItem.flammpfeil.slashblade.slashbladesilverbamboolight":135,"stat.pickup.openblocks.info_book":1,"stat.pickup.minecraft.stone":4539,"stat.craftItem.minecraft.iron_chestplate":3,"stat.pickup.minecraft.ender_pearl":4,"stat.pickup.minecraft.gold_ingot":1,"stat.killEntity.Skeleton":68,"stat.craftItem.minecraft.bookshelf":20,"stat.mineBlock.minecraft.stonebrick":5,"stat.killEntity.Chicken":90,"stat.killEntity.Spider":36,"stat.mobKills":610,"stat.mineBlock.minecraft.bookshelf":28,"stat.pickup.minecraft.quartz":106,"stat.craftItem.minecraft.fence":153,"stat.pickup.minecraft.diamond":15,"stat.mineBlock.minecraft.leaves":2659,"stat.pickup.minecraft.beetroot_seeds":159,"stat.pickup.minecraft.torch":619,"stat.mineBlock.minecraft.redstone_ore":60,"stat.craftItem.minecraft.coal_block":1,"stat.drop.minecraft.stone_axe":1,"stat.mineBlock.minecraft.stone":8578}